dynfields/__init__.py
dynfields/compat.py
dynfields/options.py
dynfields/rules.py
dynfields/web_ui.py
dynfields/htdocs/dynfields.js
dynfields/htdocs/layout.css
dynfields/htdocs/layout.js
dynfields/htdocs/rules.js
dynfields/locale/.placeholder
dynfields/locale/de/LC_MESSAGES/dynfields.mo
dynfields/locale/ja/LC_MESSAGES/dynfields.mo
dynfields/templates/prefs_panel.html
TracDynamicFields-2.5.0.dist-info/COPYING
TracDynamicFields-2.5.0.dist-info/METADATA
TracDynamicFields-2.5.0.dist-info/WHEEL
TracDynamicFields-2.5.0.dist-info/entry_points.txt
TracDynamicFields-2.5.0.dist-info/top_level.txt
TracDynamicFields-2.5.0.dist-info/RECORD
